wheelfile.py
wheelfile-0.0.9.dist-info/METADATA
wheelfile-0.0.9.dist-info/WHEEL
