Metadata-Version: 2.1
Name: wheelfile
Version: 0.0.9
Summary: API for inspecting and creating .whl files
Keywords: wheel,packaging,pip,build,distutils
Classifier: Development Status :: 2 - Pre-Alpha
Classifier: Intended Audience :: Developers
Classifier: License :: OSI Approved :: MIT License
Classifier: Topic :: Software Development :: Build Tools
Classifier: Topic :: Software Development :: Libraries
Classifier: Topic :: System :: Archiving :: Packaging
Classifier: Topic :: System :: Software Distribution
Classifier: Topic :: Utilities
Author: Błażej Michalik
Home-page: https://github.com/MrMino/wheelfile
Requires-Python: >=3.9
Requires-Dist: packaging >= 20.8
